paddleocr_cli/__init__.py
paddleocr_cli/__main__.py
paddleocr_cli/cli.py
paddleocr_cli/config.py
paddleocr_cli/ocr.py
paddleocr_cli-0.2.1.dist-info/METADATA
paddleocr_cli-0.2.1.dist-info/WHEEL
paddleocr_cli-0.2.1.dist-info/entry_points.txt
paddleocr_cli-0.2.1.dist-info/licenses/LICENSE
paddleocr_cli-0.2.1.dist-info/RECORD
