Metadata-Version: 2.4
Name: paddleocr-cli
Version: 0.2.1
Summary: A command-line tool for OCR using PaddleOCR AI Studio API
License: MIT
License-File: LICENSE
Keywords: ocr,paddleocr,cli,document,pdf
Author: PaddleOCR
Requires-Python: >=3.10,<4.0
Classifier: Development Status :: 4 - Beta
Classifier: Environment :: Console
Classifier: Intended Audience :: Developers
Classifier: License :: OSI Approved :: MIT License
Classifier: Operating System :: OS Independent
Classifier: Programming Language :: Python :: 3
Classifier: Programming Language :: Python :: 3.10
Classifier: Programming Language :: Python :: 3.11
Classifier: Programming Language :: Python :: 3.12
Classifier: Programming Language :: Python :: 3.13
Classifier: Programming Language :: Python :: 3.14
Classifier: Topic :: Text Processing
Classifier: Topic :: Utilities
Provides-Extra: yaml
Requires-Dist: pyyaml (>=6.0,<7.0) ; extra == "yaml"
